geteventplayback/README.MD
geteventplayback/__init__.py
geteventplayback/requirements.txt
geteventplayback/thirdparty.json
geteventplayback-0.10.dist-info/LICENSE.rst
geteventplayback-0.10.dist-info/METADATA
geteventplayback-0.10.dist-info/WHEEL
geteventplayback-0.10.dist-info/top_level.txt
geteventplayback-0.10.dist-info/RECORD
