Metadata-Version: 2.1
Name: geteventplayback
Version: 0.10
Summary: A pure Python module for recording and processing low-level Android input events (Mouse/Keyboard/Touchpad) - no dependencies
Home-page: https://github.com/hansalemaos/geteventplayback
Author: Johannes Fischer
Author-email: aulasparticularesdealemaosp@gmail.com
License: MIT
Keywords: Android,getevent,sendevent,record,playback
Classifier: Development Status :: 4 - Beta
Classifier: Programming Language :: Python :: 3 :: Only
Classifier: Programming Language :: Python :: 3.10
Classifier: Topic :: Software Development :: Libraries :: Python Modules
Classifier: Topic :: Utilities
License-File: LICENSE.rst
